hedgewise/__init__.py
hedgewise/_base_client.py
hedgewise/_client.py
hedgewise/_compat.py
hedgewise/_constants.py
hedgewise/_exceptions.py
hedgewise/_files.py
hedgewise/_models.py
hedgewise/_qs.py
hedgewise/_resource.py
hedgewise/_response.py
hedgewise/_streaming.py
hedgewise/_types.py
hedgewise/_version.py
hedgewise/py.typed
hedgewise/_utils/__init__.py
hedgewise/_utils/_logs.py
hedgewise/_utils/_proxy.py
hedgewise/_utils/_reflection.py
hedgewise/_utils/_resources_proxy.py
hedgewise/_utils/_streams.py
hedgewise/_utils/_sync.py
hedgewise/_utils/_transform.py
hedgewise/_utils/_typing.py
hedgewise/_utils/_utils.py
hedgewise/lib/.keep
hedgewise/resources/__init__.py
hedgewise/resources/data.py
hedgewise/resources/features.py
hedgewise/resources/forex.py
hedgewise/resources/ping.py
hedgewise/resources/supply.py
hedgewise/resources/assets/__init__.py
hedgewise/resources/assets/assets.py
hedgewise/resources/assets/futures/__init__.py
hedgewise/resources/assets/futures/forecasts.py
hedgewise/resources/assets/futures/futures.py
hedgewise/resources/assets/futures/indicators.py
hedgewise/resources/models/__init__.py
hedgewise/resources/models/models.py
hedgewise/resources/models/performance.py
hedgewise/types/__init__.py
hedgewise/types/asset_list_response.py
hedgewise/types/data_retrieve_response.py
hedgewise/types/feature_category.py
hedgewise/types/feature_get_weighted_index_params.py
hedgewise/types/feature_list_params.py
hedgewise/types/feature_list_response.py
hedgewise/types/feature_retrieve_historical_params.py
hedgewise/types/feature_retrieve_historical_response.py
hedgewise/types/feature_transform_historical_params.py
hedgewise/types/forex_data.py
hedgewise/types/forex_list_response.py
hedgewise/types/forex_retrieve_params.py
hedgewise/types/forex_retrieve_response.py
hedgewise/types/supply_list_response.py
hedgewise/types/supply_retrieve_params.py
hedgewise/types/supply_retrieve_response.py
hedgewise/types/tick.py
hedgewise/types/transformed_feature.py
hedgewise-0.1.0a3.dist-info/METADATA
hedgewise-0.1.0a3.dist-info/WHEEL
hedgewise-0.1.0a3.dist-info/licenses/LICENSE
hedgewise-0.1.0a3.dist-info/RECORD
